Metadata-Version: 1.0
Name: speval
Version: 0.1.1
Summary: Simple Parellel Function Evaluator
Home-page: https://github.com/usert5432/speval
Author: Dmitrii Torbunov
Author-email: torbu001@umn.edu
License: MIT
Platform: UNKNOWN
